<xml xmlns="http://www.w3.org/1999/xhtml"><block type="controls_whileUntil" id="MfvZ5$0,CCSDiuPj%L.T" x="50" y="110"><field name="MODE">WHILE</field><statement name="DO"><block type="niryo_one_comment" id="S%y[{(ca9Q=B0T7f.]i}"><field name="COMMENT_TEXT">Move to an observation position then</field><next><block type="controls_if" id="3y(Fgzm[5?Qxe?.nKQ`)" inline="false"><value name="IF0"><block type="niryo_one_vision_pick_w_pose" id="9fA*?bQ-~Eu{s(35^bVD"><value name="COLOR_SWITCH"><block type="niryo_one_vision_color" id="lEY;h$]4mf@mj[mkzsIB"><field name="COLOR_SELECT">ObjectColor.RED</field></block></value><value name="SHAPE_SWITCH"><block type="niryo_one_vision_shape" id="YO=Bh@A]7SCurb%WBztb"><field name="SHAPE_SELECT">ObjectShape.CIRCLE</field></block></value><value name="OBSERVATION_POSE"><block type="niryo_one_pose" id="|gxCR1UDYzQJO9:yZlL="><data>rad</data><value name="x"><block type="math_number" id="Sh4V*]i#Fy07s{T?HnzN"><field name="NUM">0.158</field></block></value><value name="y"><block type="math_number" id="jEIhI)(tihl|/B):Pjl7"><field name="NUM">0</field></block></value><value name="z"><block type="math_number" id="gH]=Zz7v@3`0hDPS{1Sm"><field name="NUM">0.2</field></block></value><value name="roll"><block type="math_number" id=":T9rh}Nhc{PdDS%6DP2d"><field name="NUM">-3.11</field></block></value><value name="pitch"><block type="math_number" id="s^Pl*Ah:~3gZk/RZB=$9"><field name="NUM">1.367</field></block></value><value name="yaw"><block type="math_number" id="}6Da3B+8-z`:{2Z,]uT1"><field name="NUM">-3.127</field></block></value></block></value><value name="WORKSPACE"><block type="niryo_one_workspace" id="/mN[~^MfBaxOBM4AV6dr"><field name="WORKSPACE_SELECT">conveyor_workspace</field></block></value><value name="HEIGHT_OFFSET"><block type="math_number" id="1^7R!NyHF@OXcAPY|0Z?"><field name="NUM">-12</field></block></value></block></value><statement name="DO0"><block type="niryo_one_comment" id="Q)q0Z)_tuRhLC)HUL)lk"><field name="COMMENT_TEXT">If an object has been taken, do:</field><next><block type="niryo_one_place_from_pose" id="(Y^:!i;PO:G;`,dr$TQD"><value name="POSE"><block type="niryo_one_pose" id="#H=o)znKrU2w];nV=lQW"><data>rad</data><value name="x"><block type="math_number" id="])lh-suDeSi?Sz|Y,:EM"><field name="NUM">-0.005</field></block></value><value name="y"><block type="math_number" id="V[uiuv+_}R5/L1U#-4BA"><field name="NUM">-0.254</field></block></value><value name="z"><block type="math_number" id="S$rRbd[,SwGnGmY4EK`t"><field name="NUM">0.062</field></block></value><value name="roll"><block type="math_number" id="t$T1txqV;Acc8YO=`;h*"><field name="NUM">-0.571</field></block></value><value name="pitch"><block type="math_number" id="uEFkB^.NzS38fX~$a;dI"><field name="NUM">1.537</field></block></value><value name="yaw"><block type="math_number" id=".VA,:#w~czK)[0*Yd@mx"><field name="NUM">-1.996</field></block></value></block></value></block></next></block></statement></block></next></block></statement></block></xml>